{
    "diy_ad_about": {
        "note_0": "自定义广告图片链接  奖励, 复活, 安装  adRate",
        "diy_ad_img_url_1": "http://t1.g.mi.com/thumbnail/webp/w900q80/Wali/15ad6443c9842c6da1857e7a1a67705e6a740f122",
        "diy_ad_img_url_2": "http://t1.g.mi.com/thumbnail/webp/w900q80/Wali/15ad6443c9842c6da1857e7a1a67705e6a740f122",
        "diy_ad_img_url_3": "http://t1.g.mi.com/thumbnail/webp/w900q80/Wali/15ad6443c9842c6da1857e7a1a67705e6a740f122"
    },
    "ads_control": {
        "note_1": "",
        "needInter": "0",
        "needBanner": "1",
        "needJiliFloat": "0",
        "needJiliAd": "0",
        "banner_interval_close_release_time": "90000",
        "needJinShanYunVideo": "1",
        "needNewFeed": "0",
        "onResumeBanner": "0",
        "isBannerTop": "0",
        "isBannerCanClose": "0",
        "hideCloseBanner": "1",
        "balanceAdRate": "1",
        "bannerAdLoadTime": "6000",
        "adRate": "100",
        "banenrAdStartTime": "30000",
        "interAndNewsFeedShowSameTime": "0",
        "useJiliNewFeed": "1",
        "isNeedSplashInter": "0",
        "bannerCloseBtUnuseRate": "20",
        "inter_interval_release_time": "3000",
        "needOpenLocCheck": "1",
        "auto_show_inter_interval_time": "300000",
        "needFloatAd": "0",
        "isADCover": "0",
        "startAttach": "1",
        "isBannerAutoHide": "0",
        "camouflage_reward_video": "0",
        "show_dialog_video": "0",
        "show_dialog_video_delay_time": "1200000",
        "download_game_packagename": "com.droidhang.ad.mi",
        "boot_show_video": "0"
    }
}
